Metadata-Version: 2.1
Name: jupyter-lsp
Version: 2.2.3
Summary: Multi-Language Server WebSocket proxy for Jupyter Notebook/Lab server
Author: jupyter-lsp Contributors
Author-email: project.jupyter@gmail.com
License: BSD-3-Clause
Project-URL: Bug Tracker, https://github.com/jupyter-lsp/jupyterlab-lsp/issues
Project-URL: Documentation, https://jupyterlab-lsp.readthedocs.io/
Project-URL: Source Code, https://github.com/jupyter-lsp/jupyterlab-lsp
Keywords: Interactive,Language Server,LSP
Classifier: Framework :: Jupyter
Classifier: Intended Audience :: Developers
Classifier: Intended Audience :: Information Technology
Classifier: License :: OSI Approved :: BSD License
Classifier: Programming Language :: Python
Requires-Python: >=3.8
License-File: LICENSE
Requires-Dist: jupyter_server>=1.1.2
Requires-Dist: importlib_metadata>=4.8.3; python_version < "3.10"
